{
  "signupUsers": [
    {
      "fullname": "Ram",
      "email": "ram@gmail.com",
      "password": "123",
      "mobile": 987654321,
      "id": 12
    },
    {
      "fullname": "jay",
      "email": "jay@gmail.com",
      "password": "12345",
      "mobile": 987654321,
      "id": 13
    },
    {
      "fullname": "admin",
      "email": "admin@gmail.com",
      "password": "admin123",
      "mobile": 9876543232,
      "id": 14
    },
    {
      "fullname": "chandu",
      "email": "chandu@gmail.com",
      "password": "chandu123",
      "mobile": 12345678,
      "id": 16
    },
    {
      "fullname": "jagadish",
      "email": "jagadish@gmail.com",
      "password": "123",
      "mobile": 987654321,
      "id": 17
    }
  ],
  "productList": [
    {
      "productName": "mobile",
      "category": "Electronics",
      "date": "2022-07-30T18:30:00.000Z",
      "freshness": "Brand New",
      "price": 20000,
      "Comment": "new",
      "id": 1
    },
    {
      "productName": "laptop",
      "category": "Electronics",
      "date": "2022-08-03T18:30:00.000Z",
      "freshness": "Brand New",
      "price": 20000,
      "Comment": "new",
      "id": 2
    },
    {
      "productName": "tamoto",
      "category": "Vegetables",
      "date": "2022-07-31T18:30:00.000Z",
      "freshness": "Brand New",
      "price": 25,
      "Comment": "freshly",
      "id": 3
    },
    {
      "productName": "headphones",
      "category": "Electronics",
      "date": "2022-07-28T18:30:00.000Z",
      "freshness": "Brand New",
      "price": 5000,
      "Comment": "new",
      "id": 4
    }
  ],
  "profile": {
    "name": "typicode"
  }
}